{
	"configurations" : 
	[
		{
			"directories" : 
			[
				{
					"build" : ".",
					"childIndexes" : 
					[
						1
					],
					"hasInstallRule" : true,
					"minimumCMakeVersion" : 
					{
						"string" : "3.12.4"
					},
					"projectIndex" : 0,
					"source" : ".",
					"targetIndexes" : 
					[
						0,
						1,
						2,
						3,
						4,
						5,
						6,
						7,
						8,
						9,
						10,
						11,
						12,
						13,
						14,
						15,
						16,
						17,
						18,
						19,
						20,
						21,
						22,
						23,
						24,
						25,
						26,
						27,
						28,
						31
					]
				},
				{
					"build" : "ext/parmetis",
					"childIndexes" : 
					[
						2,
						3,
						4,
						5
					],
					"hasInstallRule" : true,
					"minimumCMakeVersion" : 
					{
						"string" : "3.0.0"
					},
					"parentIndex" : 0,
					"projectIndex" : 1,
					"source" : "ext/parmetis"
				},
				{
					"build" : "ext/parmetis/metis/libmetis",
					"hasInstallRule" : true,
					"minimumCMakeVersion" : 
					{
						"string" : "3.0.0"
					},
					"parentIndex" : 1,
					"projectIndex" : 1,
					"source" : "ext/parmetis/metis/libmetis",
					"targetIndexes" : 
					[
						29
					]
				},
				{
					"build" : "ext/parmetis/metis/include",
					"hasInstallRule" : true,
					"minimumCMakeVersion" : 
					{
						"string" : "3.0.0"
					},
					"parentIndex" : 1,
					"projectIndex" : 1,
					"source" : "ext/parmetis/metis/include"
				},
				{
					"build" : "ext/parmetis/include",
					"hasInstallRule" : true,
					"minimumCMakeVersion" : 
					{
						"string" : "3.0.0"
					},
					"parentIndex" : 1,
					"projectIndex" : 1,
					"source" : "ext/parmetis/include"
				},
				{
					"build" : "ext/parmetis/libparmetis",
					"hasInstallRule" : true,
					"minimumCMakeVersion" : 
					{
						"string" : "3.0.0"
					},
					"parentIndex" : 1,
					"projectIndex" : 1,
					"source" : "ext/parmetis/libparmetis",
					"targetIndexes" : 
					[
						30
					]
				}
			],
			"name" : "Release",
			"projects" : 
			[
				{
					"childIndexes" : 
					[
						1
					],
					"directoryIndexes" : 
					[
						0
					],
					"name" : "KiT-RT",
					"targetIndexes" : 
					[
						0,
						1,
						2,
						3,
						4,
						5,
						6,
						7,
						8,
						9,
						10,
						11,
						12,
						13,
						14,
						15,
						16,
						17,
						18,
						19,
						20,
						21,
						22,
						23,
						24,
						25,
						26,
						27,
						28,
						31
					]
				},
				{
					"directoryIndexes" : 
					[
						1,
						2,
						3,
						4,
						5
					],
					"name" : "ParMETIS",
					"parentIndex" : 0,
					"targetIndexes" : 
					[
						29,
						30
					]
				}
			],
			"targets" : 
			[
				{
					"directoryIndex" : 0,
					"id" : "Continuous::@6890427a1f51a3e7e1df",
					"jsonFile" : "target-Continuous-Release-dfaa64a18a6c408e6de9.json",
					"name" : "Continuous",
					"projectIndex" : 0
				},
				{
					"directoryIndex" : 0,
					"id" : "ContinuousBuild::@6890427a1f51a3e7e1df",
					"jsonFile" : "target-ContinuousBuild-Release-b14faf37afced5f952c4.json",
					"name" : "ContinuousBuild",
					"projectIndex" : 0
				},
				{
					"directoryIndex" : 0,
					"id" : "ContinuousConfigure::@6890427a1f51a3e7e1df",
					"jsonFile" : "target-ContinuousConfigure-Release-decbba99abd66019f40c.json",
					"name" : "ContinuousConfigure",
					"projectIndex" : 0
				},
				{
					"directoryIndex" : 0,
					"id" : "ContinuousCoverage::@6890427a1f51a3e7e1df",
					"jsonFile" : "target-ContinuousCoverage-Release-153ab3e4e2579e021b8d.json",
					"name" : "ContinuousCoverage",
					"projectIndex" : 0
				},
				{
					"directoryIndex" : 0,
					"id" : "ContinuousMemCheck::@6890427a1f51a3e7e1df",
					"jsonFile" : "target-ContinuousMemCheck-Release-ef308015b6e2b1214bfc.json",
					"name" : "ContinuousMemCheck",
					"projectIndex" : 0
				},
				{
					"directoryIndex" : 0,
					"id" : "ContinuousStart::@6890427a1f51a3e7e1df",
					"jsonFile" : "target-ContinuousStart-Release-d896ece72452224ae615.json",
					"name" : "ContinuousStart",
					"projectIndex" : 0
				},
				{
					"directoryIndex" : 0,
					"id" : "ContinuousSubmit::@6890427a1f51a3e7e1df",
					"jsonFile" : "target-ContinuousSubmit-Release-60f41213fe18d06b249a.json",
					"name" : "ContinuousSubmit",
					"projectIndex" : 0
				},
				{
					"directoryIndex" : 0,
					"id" : "ContinuousTest::@6890427a1f51a3e7e1df",
					"jsonFile" : "target-ContinuousTest-Release-a28145235fc645b036fc.json",
					"name" : "ContinuousTest",
					"projectIndex" : 0
				},
				{
					"directoryIndex" : 0,
					"id" : "ContinuousUpdate::@6890427a1f51a3e7e1df",
					"jsonFile" : "target-ContinuousUpdate-Release-7e6689f49e7bf7ca836a.json",
					"name" : "ContinuousUpdate",
					"projectIndex" : 0
				},
				{
					"directoryIndex" : 0,
					"id" : "Experimental::@6890427a1f51a3e7e1df",
					"jsonFile" : "target-Experimental-Release-1bd2c16bacb0c2baeaf7.json",
					"name" : "Experimental",
					"projectIndex" : 0
				},
				{
					"directoryIndex" : 0,
					"id" : "ExperimentalBuild::@6890427a1f51a3e7e1df",
					"jsonFile" : "target-ExperimentalBuild-Release-315b8b8bf0e353bf78c1.json",
					"name" : "ExperimentalBuild",
					"projectIndex" : 0
				},
				{
					"directoryIndex" : 0,
					"id" : "ExperimentalConfigure::@6890427a1f51a3e7e1df",
					"jsonFile" : "target-ExperimentalConfigure-Release-f0950dace35e94f24870.json",
					"name" : "ExperimentalConfigure",
					"projectIndex" : 0
				},
				{
					"directoryIndex" : 0,
					"id" : "ExperimentalCoverage::@6890427a1f51a3e7e1df",
					"jsonFile" : "target-ExperimentalCoverage-Release-bbc5568e0fc25d59a5db.json",
					"name" : "ExperimentalCoverage",
					"projectIndex" : 0
				},
				{
					"directoryIndex" : 0,
					"id" : "ExperimentalMemCheck::@6890427a1f51a3e7e1df",
					"jsonFile" : "target-ExperimentalMemCheck-Release-7db4f5611759210f0e78.json",
					"name" : "ExperimentalMemCheck",
					"projectIndex" : 0
				},
				{
					"directoryIndex" : 0,
					"id" : "ExperimentalStart::@6890427a1f51a3e7e1df",
					"jsonFile" : "target-ExperimentalStart-Release-94c8a8fdb02d2b6f1e79.json",
					"name" : "ExperimentalStart",
					"projectIndex" : 0
				},
				{
					"directoryIndex" : 0,
					"id" : "ExperimentalSubmit::@6890427a1f51a3e7e1df",
					"jsonFile" : "target-ExperimentalSubmit-Release-19d601fc72f3ba3a772e.json",
					"name" : "ExperimentalSubmit",
					"projectIndex" : 0
				},
				{
					"directoryIndex" : 0,
					"id" : "ExperimentalTest::@6890427a1f51a3e7e1df",
					"jsonFile" : "target-ExperimentalTest-Release-c856fc62843e21305735.json",
					"name" : "ExperimentalTest",
					"projectIndex" : 0
				},
				{
					"directoryIndex" : 0,
					"id" : "ExperimentalUpdate::@6890427a1f51a3e7e1df",
					"jsonFile" : "target-ExperimentalUpdate-Release-04187af4079205cfa36e.json",
					"name" : "ExperimentalUpdate",
					"projectIndex" : 0
				},
				{
					"directoryIndex" : 0,
					"id" : "KiT-RT::@6890427a1f51a3e7e1df",
					"jsonFile" : "target-KiT-RT-Release-4f78dfe96de0ecc8f791.json",
					"name" : "KiT-RT",
					"projectIndex" : 0
				},
				{
					"directoryIndex" : 0,
					"id" : "Nightly::@6890427a1f51a3e7e1df",
					"jsonFile" : "target-Nightly-Release-7dad0dcbae5d59f8c1fb.json",
					"name" : "Nightly",
					"projectIndex" : 0
				},
				{
					"directoryIndex" : 0,
					"id" : "NightlyBuild::@6890427a1f51a3e7e1df",
					"jsonFile" : "target-NightlyBuild-Release-5e44298bdbcb9abf2c0e.json",
					"name" : "NightlyBuild",
					"projectIndex" : 0
				},
				{
					"directoryIndex" : 0,
					"id" : "NightlyConfigure::@6890427a1f51a3e7e1df",
					"jsonFile" : "target-NightlyConfigure-Release-960d8719213fc3e53dc6.json",
					"name" : "NightlyConfigure",
					"projectIndex" : 0
				},
				{
					"directoryIndex" : 0,
					"id" : "NightlyCoverage::@6890427a1f51a3e7e1df",
					"jsonFile" : "target-NightlyCoverage-Release-e191d7b57d2c8bd8803d.json",
					"name" : "NightlyCoverage",
					"projectIndex" : 0
				},
				{
					"directoryIndex" : 0,
					"id" : "NightlyMemCheck::@6890427a1f51a3e7e1df",
					"jsonFile" : "target-NightlyMemCheck-Release-79069913029d55b2bc4c.json",
					"name" : "NightlyMemCheck",
					"projectIndex" : 0
				},
				{
					"directoryIndex" : 0,
					"id" : "NightlyMemoryCheck::@6890427a1f51a3e7e1df",
					"jsonFile" : "target-NightlyMemoryCheck-Release-cb6097807eab180d14d5.json",
					"name" : "NightlyMemoryCheck",
					"projectIndex" : 0
				},
				{
					"directoryIndex" : 0,
					"id" : "NightlyStart::@6890427a1f51a3e7e1df",
					"jsonFile" : "target-NightlyStart-Release-bfe984c859ec22a2b42f.json",
					"name" : "NightlyStart",
					"projectIndex" : 0
				},
				{
					"directoryIndex" : 0,
					"id" : "NightlySubmit::@6890427a1f51a3e7e1df",
					"jsonFile" : "target-NightlySubmit-Release-d1959d79962fab1a66d3.json",
					"name" : "NightlySubmit",
					"projectIndex" : 0
				},
				{
					"directoryIndex" : 0,
					"id" : "NightlyTest::@6890427a1f51a3e7e1df",
					"jsonFile" : "target-NightlyTest-Release-af0499b6ddf75b0b10c3.json",
					"name" : "NightlyTest",
					"projectIndex" : 0
				},
				{
					"directoryIndex" : 0,
					"id" : "NightlyUpdate::@6890427a1f51a3e7e1df",
					"jsonFile" : "target-NightlyUpdate-Release-93ed6630249100c90d34.json",
					"name" : "NightlyUpdate",
					"projectIndex" : 0
				},
				{
					"directoryIndex" : 2,
					"id" : "metis::@e8373f7f43541535e3f7",
					"jsonFile" : "target-metis-Release-f02897999796871da890.json",
					"name" : "metis",
					"projectIndex" : 1
				},
				{
					"directoryIndex" : 5,
					"id" : "parmetis::@212a7c010ff248a08388",
					"jsonFile" : "target-parmetis-Release-33bfc192be88645b9190.json",
					"name" : "parmetis",
					"projectIndex" : 1
				},
				{
					"directoryIndex" : 0,
					"id" : "unit_tests::@6890427a1f51a3e7e1df",
					"jsonFile" : "target-unit_tests-Release-0cf10f85e6a8a475a64a.json",
					"name" : "unit_tests",
					"projectIndex" : 0
				}
			]
		}
	],
	"kind" : "codemodel",
	"paths" : 
	{
		"build" : "/home/jonas/Projects/rtsn/build-code-Desktop-Release",
		"source" : "/home/jonas/Projects/rtsn/code"
	},
	"version" : 
	{
		"major" : 2,
		"minor" : 2
	}
}
